README.md
setup.py
pytorch_categorical/__init__.py
pytorch_categorical/categorical.py
pytorch_categorical/test.py
pytorch_categorical.egg-info/PKG-INFO
pytorch_categorical.egg-info/SOURCES.txt
pytorch_categorical.egg-info/dependency_links.txt
pytorch_categorical.egg-info/top_level.txt