Metadata-Version: 2.1
Name: pytorch-categorical
Version: 0.0.3
Summary: Draw a large number of samples from a categorical distribution with large support on the GPU using Pytorch.
Home-page: https://github.com/enewe101/pytorch-categorical
Author: Edward Newell
Author-email: edward.newell@gmail.com
License: UNKNOWN
Platform: UNKNOWN
Classifier: Programming Language :: Python :: 3
Classifier: License :: OSI Approved :: MIT License
Classifier: Operating System :: OS Independent
